ansys/openapi/common/__init__.py
ansys/openapi/common/_api_client.py
ansys/openapi/common/_base/__init__.py
ansys/openapi/common/_base/_types.py
ansys/openapi/common/_exceptions.py
ansys/openapi/common/_logger.py
ansys/openapi/common/_oidc.py
ansys/openapi/common/_session.py
ansys/openapi/common/_util.py
ansys/openapi/common/py.typed
ansys_openapi_common-2.3.2.dist-info/METADATA
ansys_openapi_common-2.3.2.dist-info/WHEEL
ansys_openapi_common-2.3.2.dist-info/licenses/AUTHORS
ansys_openapi_common-2.3.2.dist-info/licenses/LICENSE
ansys_openapi_common-2.3.2.dist-info/RECORD
