Metadata-Version: 2.4
Name: ansys-openapi-common
Version: 2.3.2
Summary: Provides a helper to create sessions for use with Ansys OpenAPI clients.
License: MIT
License-File: AUTHORS
License-File: LICENSE
Keywords: Ansys,OpenAPI
Author: ANSYS, Inc.
Author-email: pyansys.core@ansys.com
Maintainer: ANSYS, Inc.
Maintainer-email: pyansys.core@ansys.com
Requires-Python: >=3.10,<4.0
Classifier: Development Status :: 5 - Production/Stable
Classifier: Intended Audience :: Science/Research
Classifier: License :: OSI Approved :: MIT License
Classifier: Operating System :: MacOS
Classifier: Operating System :: Microsoft :: Windows
Classifier: Operating System :: POSIX
Classifier: Programming Language :: Python :: 3
Classifier: Programming Language :: Python :: 3.10
Classifier: Programming Language :: Python :: 3.11
Classifier: Programming Language :: Python :: 3.12
Classifier: Programming Language :: Python :: 3.13
Classifier: Programming Language :: Python :: 3.14
Classifier: Topic :: Scientific/Engineering :: Information Analysis
Provides-Extra: linux-kerberos
Provides-Extra: oidc
Requires-Dist: keyring (>=22,<26) ; extra == "oidc"
Requires-Dist: pyparsing (>=3.0.8,<4.0.0)
Requires-Dist: python-dateutil (>=2.9,<3.0)
Requires-Dist: requests (>=2.26,<3.0)
Requires-Dist: requests-kerberos (>=0.13,<0.16) ; (sys_platform == "linux") and (extra == "linux-kerberos")
Requires-Dist: requests-negotiate-sspi (>=0.5.2,<0.6.0) ; sys_platform == "win32"
Requires-Dist: requests-ntlm (>=1.1.0,<2.0.0)
Requires-Dist: requests_auth (>=8.0.0,<9.0.0) ; extra == "oidc"
Project-URL: Documentation, https://openapi.docs.pyansys.com
Project-URL: Repository, https://github.com/ansys/openapi-common
